{"runId":"d75f4a89-740d-4a70-a89e-2e09374fb945_02-18-week1-FAILING_AND_PASSING","buildId":338152503,"containerId":"N/A","dateReproducedBuildStr":"22/08/18 03:56","dateReproducedBuild":{"$date":"2018-08-22T03:56:07.748Z"},"dayReproducedBuild":"22/08/2018","hostname":"spirals-bears","status":"DETECTED"}
{"runId":"d75f4a89-740d-4a70-a89e-2e09374fb945_02-18-week1-FAILING_AND_PASSING","buildId":336714986,"containerId":"N/A","dateReproducedBuildStr":"22/08/18 03:56","dateReproducedBuild":{"$date":"2018-08-22T03:56:07.839Z"},"dayReproducedBuild":"22/08/2018","hostname":"spirals-bears","status":"DETECTED"}
{"runId":"d75f4a89-740d-4a70-a89e-2e09374fb945_02-18-week1-FAILING_AND_PASSING","buildId":336745613,"containerId":"N/A","dateReproducedBuildStr":"22/08/18 03:56","dateReproducedBuild":{"$date":"2018-08-22T03:56:07.919Z"},"dayReproducedBuild":"22/08/2018","hostname":"spirals-bears","status":"DETECTED"}
{"runId":"d75f4a89-740d-4a70-a89e-2e09374fb945_02-18-week1-FAILING_AND_PASSING","buildId":335905968,"containerId":"N/A","dateReproducedBuildStr":"22/08/18 03:56","dateReproducedBuild":{"$date":"2018-08-22T03:56:07.953Z"},"dayReproducedBuild":"22/08/2018","hostname":"spirals-bears","status":"DETECTED"}
{"runId":"d75f4a89-740d-4a70-a89e-2e09374fb945_02-18-week1-FAILING_AND_PASSING","buildId":335815306,"containerId":"N/A","dateReproducedBuildStr":"22/08/18 03:56","dateReproducedBuild":{"$date":"2018-08-22T03:56:07.955Z"},"dayReproducedBuild":"22/08/2018","hostname":"spirals-bears","status":"DETECTED"}
{"runId":"d75f4a89-740d-4a70-a89e-2e09374fb945_02-18-week1-FAILING_AND_PASSING","buildId":336824539,"containerId":"N/A","dateReproducedBuildStr":"22/08/18 03:56","dateReproducedBuild":{"$date":"2018-08-22T03:56:07.959Z"},"dayReproducedBuild":"22/08/2018","hostname":"spirals-bears","status":"DETECTED"}
{"runId":"d75f4a89-740d-4a70-a89e-2e09374fb945_02-18-week1-FAILING_AND_PASSING","buildId":338593327,"containerId":"N/A","dateReproducedBuildStr":"22/08/18 03:56","dateReproducedBuild":{"$date":"2018-08-22T03:56:07.963Z"},"dayReproducedBuild":"22/08/2018","hostname":"spirals-bears","status":"DETECTED"}
{"runId":"d75f4a89-740d-4a70-a89e-2e09374fb945_02-18-week1-FAILING_AND_PASSING","buildId":337776497,"containerId":"N/A","dateReproducedBuildStr":"22/08/18 03:56","dateReproducedBuild":{"$date":"2018-08-22T03:56:07.967Z"},"dayReproducedBuild":"22/08/2018","hostname":"spirals-bears","status":"DETECTED"}
{"runId":"d75f4a89-740d-4a70-a89e-2e09374fb945_02-18-week1-FAILING_AND_PASSING","buildId":337745166,"containerId":"N/A","dateReproducedBuildStr":"22/08/18 03:56","dateReproducedBuild":{"$date":"2018-08-22T03:56:07.969Z"},"dayReproducedBuild":"22/08/2018","hostname":"spirals-bears","status":"DETECTED"}
{"runId":"d75f4a89-740d-4a70-a89e-2e09374fb945_02-18-week1-FAILING_AND_PASSING","buildId":336592736,"containerId":"N/A","dateReproducedBuildStr":"22/08/18 03:56","dateReproducedBuild":{"$date":"2018-08-22T03:56:07.970Z"},"dayReproducedBuild":"22/08/2018","hostname":"spirals-bears","status":"DETECTED"}
{"runId":"d75f4a89-740d-4a70-a89e-2e09374fb945_02-18-week1-FAILING_AND_PASSING","buildId":336398116,"containerId":"N/A","dateReproducedBuildStr":"22/08/18 03:56","dateReproducedBuild":{"$date":"2018-08-22T03:56:07.972Z"},"dayReproducedBuild":"22/08/2018","hostname":"spirals-bears","status":"DETECTED"}
{"runId":"d75f4a89-740d-4a70-a89e-2e09374fb945_02-18-week1-FAILING_AND_PASSING","buildId":337368511,"containerId":"N/A","dateReproducedBuildStr":"22/08/18 03:56","dateReproducedBuild":{"$date":"2018-08-22T03:56:07.977Z"},"dayReproducedBuild":"22/08/2018","hostname":"spirals-bears","status":"DETECTED"}
{"runId":"d75f4a89-740d-4a70-a89e-2e09374fb945_02-18-week1-FAILING_AND_PASSING","buildId":337255850,"containerId":"N/A","dateReproducedBuildStr":"22/08/18 03:56","dateReproducedBuild":{"$date":"2018-08-22T03:56:07.977Z"},"dayReproducedBuild":"22/08/2018","hostname":"spirals-bears","status":"DETECTED"}
{"runId":"d75f4a89-740d-4a70-a89e-2e09374fb945_02-18-week1-FAILING_AND_PASSING","buildId":337040912,"containerId":"N/A","dateReproducedBuildStr":"22/08/18 03:56","dateReproducedBuild":{"$date":"2018-08-22T03:56:07.978Z"},"dayReproducedBuild":"22/08/2018","hostname":"spirals-bears","status":"DETECTED"}
{"runId":"d75f4a89-740d-4a70-a89e-2e09374fb945_02-18-week1-FAILING_AND_PASSING","buildId":337972530,"containerId":"N/A","dateReproducedBuildStr":"22/08/18 03:56","dateReproducedBuild":{"$date":"2018-08-22T03:56:07.994Z"},"dayReproducedBuild":"22/08/2018","hostname":"spirals-bears","status":"DETECTED"}
{"runId":"d75f4a89-740d-4a70-a89e-2e09374fb945_02-18-week1-FAILING_AND_PASSING","buildId":337736892,"containerId":"N/A","dateReproducedBuildStr":"22/08/18 03:56","dateReproducedBuild":{"$date":"2018-08-22T03:56:07.995Z"},"dayReproducedBuild":"22/08/2018","hostname":"spirals-bears","status":"DETECTED"}
{"runId":"d75f4a89-740d-4a70-a89e-2e09374fb945_02-18-week1-FAILING_AND_PASSING","buildId":337736851,"containerId":"N/A","dateReproducedBuildStr":"22/08/18 03:56","dateReproducedBuild":{"$date":"2018-08-22T03:56:07.996Z"},"dayReproducedBuild":"22/08/2018","hostname":"spirals-bears","status":"DETECTED"}
{"runId":"d75f4a89-740d-4a70-a89e-2e09374fb945_02-18-week1-FAILING_AND_PASSING","buildId":337254943,"containerId":"N/A","dateReproducedBuildStr":"22/08/18 03:56","dateReproducedBuild":{"$date":"2018-08-22T03:56:07.997Z"},"dayReproducedBuild":"22/08/2018","hostname":"spirals-bears","status":"DETECTED"}
{"runId":"d75f4a89-740d-4a70-a89e-2e09374fb945_02-18-week1-FAILING_AND_PASSING","buildId":336932501,"containerId":"N/A","dateReproducedBuildStr":"22/08/18 03:56","dateReproducedBuild":{"$date":"2018-08-22T03:56:08.010Z"},"dayReproducedBuild":"22/08/2018","hostname":"spirals-bears","status":"DETECTED"}
{"runId":"d75f4a89-740d-4a70-a89e-2e09374fb945_02-18-week1-FAILING_AND_PASSING","buildId":337909441,"containerId":"N/A","dateReproducedBuildStr":"22/08/18 03:56","dateReproducedBuild":{"$date":"2018-08-22T03:56:08.025Z"},"dayReproducedBuild":"22/08/2018","hostname":"spirals-bears","status":"DETECTED"}
{"runId":"d75f4a89-740d-4a70-a89e-2e09374fb945_02-18-week1-FAILING_AND_PASSING","buildId":338603736,"containerId":"N/A","dateReproducedBuildStr":"22/08/18 03:56","dateReproducedBuild":{"$date":"2018-08-22T03:56:08.026Z"},"dayReproducedBuild":"22/08/2018","hostname":"spirals-bears","status":"DETECTED"}
{"runId":"d75f4a89-740d-4a70-a89e-2e09374fb945_02-18-week1-FAILING_AND_PASSING","buildId":337535538,"containerId":"N/A","dateReproducedBuildStr":"22/08/18 03:56","dateReproducedBuild":{"$date":"2018-08-22T03:56:08.027Z"},"dayReproducedBuild":"22/08/2018","hostname":"spirals-bears","status":"DETECTED"}
{"runId":"d75f4a89-740d-4a70-a89e-2e09374fb945_02-18-week1-FAILING_AND_PASSING","buildId":338121462,"containerId":"N/A","dateReproducedBuildStr":"22/08/18 03:56","dateReproducedBuild":{"$date":"2018-08-22T03:56:08.028Z"},"dayReproducedBuild":"22/08/2018","hostname":"spirals-bears","status":"DETECTED"}
{"runId":"d75f4a89-740d-4a70-a89e-2e09374fb945_02-18-week1-FAILING_AND_PASSING","buildId":336563220,"containerId":"N/A","dateReproducedBuildStr":"22/08/18 03:56","dateReproducedBuild":{"$date":"2018-08-22T03:56:08.042Z"},"dayReproducedBuild":"22/08/2018","hostname":"spirals-bears","status":"DETECTED"}
{"runId":"d75f4a89-740d-4a70-a89e-2e09374fb945_02-18-week1-FAILING_AND_PASSING","buildId":338439832,"containerId":"N/A","dateReproducedBuildStr":"22/08/18 03:56","dateReproducedBuild":{"$date":"2018-08-22T03:56:08.044Z"},"dayReproducedBuild":"22/08/2018","hostname":"spirals-bears","status":"DETECTED"}
{"runId":"d75f4a89-740d-4a70-a89e-2e09374fb945_02-18-week1-FAILING_AND_PASSING","buildId":338016101,"containerId":"N/A","dateReproducedBuildStr":"22/08/18 03:56","dateReproducedBuild":{"$date":"2018-08-22T03:56:08.045Z"},"dayReproducedBuild":"22/08/2018","hostname":"spirals-bears","status":"DETECTED"}
{"runId":"d75f4a89-740d-4a70-a89e-2e09374fb945_02-18-week1-FAILING_AND_PASSING","buildId":335027721,"containerId":"N/A","dateReproducedBuildStr":"22/08/18 03:56","dateReproducedBuild":{"$date":"2018-08-22T03:56:08.062Z"},"dayReproducedBuild":"22/08/2018","hostname":"spirals-bears","status":"DETECTED"}
{"runId":"d75f4a89-740d-4a70-a89e-2e09374fb945_02-18-week1-FAILING_AND_PASSING","buildId":338152503,"containerId":"9e03c2906faca7085c67f4c81327ac6b984dc95878a02053c6bb1b11182a9444","dateReproducedBuildStr":"22/08/18 04:37","dateReproducedBuild":{"$date":"2018-08-22T04:37:34.486Z"},"dayReproducedBuild":"22/08/2018","hostname":"spirals-bears","status":"TREATED"}
{"runId":"d75f4a89-740d-4a70-a89e-2e09374fb945_02-18-week1-FAILING_AND_PASSING","buildId":336714986,"containerId":"f4f3a026db44f39d13532b17f7da2af268c8f8e8c0eee8585c4223d5611f8999","dateReproducedBuildStr":"22/08/18 07:54","dateReproducedBuild":{"$date":"2018-08-22T07:54:23.993Z"},"dayReproducedBuild":"22/08/2018","hostname":"spirals-bears","status":"TREATED"}
{"runId":"d75f4a89-740d-4a70-a89e-2e09374fb945_02-18-week1-FAILING_AND_PASSING","buildId":336745613,"containerId":"2e0ea4b5be90456fe598d374926c10fb404799367b87948c7f86598bf32b35dc","dateReproducedBuildStr":"22/08/18 09:07","dateReproducedBuild":{"$date":"2018-08-22T09:07:39.231Z"},"dayReproducedBuild":"22/08/2018","hostname":"spirals-bears","status":"TREATED"}
{"runId":"d75f4a89-740d-4a70-a89e-2e09374fb945_02-18-week1-FAILING_AND_PASSING","buildId":335905968,"containerId":"c1d763a2f9a386fd114d4fdc3edaf28bed5b2076c43fffe16f046373395a7ffc","dateReproducedBuildStr":"22/08/18 09:17","dateReproducedBuild":{"$date":"2018-08-22T09:17:40.098Z"},"dayReproducedBuild":"22/08/2018","hostname":"spirals-bears","status":"TREATED"}
{"runId":"d75f4a89-740d-4a70-a89e-2e09374fb945_02-18-week1-FAILING_AND_PASSING","buildId":335815306,"containerId":"e578cc05bc5f59c7ffdb93fae81f2a652989159e4e2e30a844e82c132c071f2b","dateReproducedBuildStr":"22/08/18 09:20","dateReproducedBuild":{"$date":"2018-08-22T09:20:56.110Z"},"dayReproducedBuild":"22/08/2018","hostname":"spirals-bears","status":"TREATED"}
{"runId":"d75f4a89-740d-4a70-a89e-2e09374fb945_02-18-week1-FAILING_AND_PASSING","buildId":336824539,"containerId":"7958fc69141a8d5a43219a5937a95b30f65c8db4ea53b53c8902653156237312","dateReproducedBuildStr":"22/08/18 09:26","dateReproducedBuild":{"$date":"2018-08-22T09:26:51.362Z"},"dayReproducedBuild":"22/08/2018","hostname":"spirals-bears","status":"TREATED"}
{"runId":"d75f4a89-740d-4a70-a89e-2e09374fb945_02-18-week1-FAILING_AND_PASSING","buildId":338593327,"containerId":"d7f82cd55c080885674d835d1f47da54f15198309aff4d0123e0800c4cdfd901","dateReproducedBuildStr":"22/08/18 09:46","dateReproducedBuild":{"$date":"2018-08-22T09:46:25.217Z"},"dayReproducedBuild":"22/08/2018","hostname":"spirals-bears","status":"TREATED"}
{"runId":"d75f4a89-740d-4a70-a89e-2e09374fb945_02-18-week1-FAILING_AND_PASSING","buildId":337776497,"containerId":"395ad767d9e836aad8f912ecd3f6f8e3ed1798168b5828ad173c6422ad129b27","dateReproducedBuildStr":"22/08/18 10:02","dateReproducedBuild":{"$date":"2018-08-22T10:02:26.406Z"},"dayReproducedBuild":"22/08/2018","hostname":"spirals-bears","status":"TREATED"}
{"runId":"d75f4a89-740d-4a70-a89e-2e09374fb945_02-18-week1-FAILING_AND_PASSING","buildId":337745166,"containerId":"b6f7f09380b723196abb018e40f0ea8bf274ad329585cb5a39da3ab24877077c","dateReproducedBuildStr":"22/08/18 10:15","dateReproducedBuild":{"$date":"2018-08-22T10:15:30.744Z"},"dayReproducedBuild":"22/08/2018","hostname":"spirals-bears","status":"TREATED"}
{"runId":"d75f4a89-740d-4a70-a89e-2e09374fb945_02-18-week1-FAILING_AND_PASSING","buildId":336592736,"containerId":"664d3644fa3612619f3c3552250f814c84727599b236c376b6b672be898212a2","dateReproducedBuildStr":"22/08/18 10:16","dateReproducedBuild":{"$date":"2018-08-22T10:16:31.648Z"},"dayReproducedBuild":"22/08/2018","hostname":"spirals-bears","status":"TREATED"}
{"runId":"d75f4a89-740d-4a70-a89e-2e09374fb945_02-18-week1-FAILING_AND_PASSING","buildId":336398116,"containerId":"3e5c0e5d79eb3a71201666b276bebcbf3fae5ca225dc7e402b79bdb70080c0a1","dateReproducedBuildStr":"22/08/18 10:26","dateReproducedBuild":{"$date":"2018-08-22T10:26:06.080Z"},"dayReproducedBuild":"22/08/2018","hostname":"spirals-bears","status":"TREATED"}
{"runId":"d75f4a89-740d-4a70-a89e-2e09374fb945_02-18-week1-FAILING_AND_PASSING","buildId":337368511,"containerId":"61f124a384604e6daf41c6a620f42eae5a8aa800bd8bbde745591824b444a2d6","dateReproducedBuildStr":"22/08/18 10:33","dateReproducedBuild":{"$date":"2018-08-22T10:33:29.489Z"},"dayReproducedBuild":"22/08/2018","hostname":"spirals-bears","status":"TREATED"}
{"runId":"d75f4a89-740d-4a70-a89e-2e09374fb945_02-18-week1-FAILING_AND_PASSING","buildId":337255850,"containerId":"0d58d64f3bded302be034cc890955cb4c79ecbe3e362c7e0d65b8c9d841fa491","dateReproducedBuildStr":"22/08/18 10:34","dateReproducedBuild":{"$date":"2018-08-22T10:34:09.924Z"},"dayReproducedBuild":"22/08/2018","hostname":"spirals-bears","status":"TREATED"}
{"runId":"d75f4a89-740d-4a70-a89e-2e09374fb945_02-18-week1-FAILING_AND_PASSING","buildId":337972530,"containerId":"ee1718e854191cda42d01ebe9387e5e2a8603d5b69f4ae3adac4ff128acf86f8","dateReproducedBuildStr":"22/08/18 10:40","dateReproducedBuild":{"$date":"2018-08-22T10:40:11.366Z"},"dayReproducedBuild":"22/08/2018","hostname":"spirals-bears","status":"TREATED"}
{"runId":"d75f4a89-740d-4a70-a89e-2e09374fb945_02-18-week1-FAILING_AND_PASSING","buildId":337736892,"containerId":"3bb17b32fb0cb2147fb0cacc7489b2e10f38689ffcbd44a742f4bc6957e3b671","dateReproducedBuildStr":"22/08/18 10:40","dateReproducedBuild":{"$date":"2018-08-22T10:40:38.678Z"},"dayReproducedBuild":"22/08/2018","hostname":"spirals-bears","status":"TREATED"}
{"runId":"d75f4a89-740d-4a70-a89e-2e09374fb945_02-18-week1-FAILING_AND_PASSING","buildId":337736851,"containerId":"f78ededde50ab8d74c03f79cd64fe225a75a91d501d77147a8a7286820f72280","dateReproducedBuildStr":"22/08/18 10:41","dateReproducedBuild":{"$date":"2018-08-22T10:41:00.676Z"},"dayReproducedBuild":"22/08/2018","hostname":"spirals-bears","status":"TREATED"}
{"runId":"d75f4a89-740d-4a70-a89e-2e09374fb945_02-18-week1-FAILING_AND_PASSING","buildId":337040912,"containerId":"793641efc4cf1563ffaded541da4de11b2d73501604365bf8a84a533a3faf8ac","dateReproducedBuildStr":"22/08/18 10:43","dateReproducedBuild":{"$date":"2018-08-22T10:43:37.688Z"},"dayReproducedBuild":"22/08/2018","hostname":"spirals-bears","status":"TREATED"}
{"runId":"d75f4a89-740d-4a70-a89e-2e09374fb945_02-18-week1-FAILING_AND_PASSING","buildId":336932501,"containerId":"7c111b230cda272823226aae7cef402ec40aa2af43ab0cf097615cc3c6f413fb","dateReproducedBuildStr":"22/08/18 10:46","dateReproducedBuild":{"$date":"2018-08-22T10:46:23.642Z"},"dayReproducedBuild":"22/08/2018","hostname":"spirals-bears","status":"TREATED"}
{"runId":"d75f4a89-740d-4a70-a89e-2e09374fb945_02-18-week1-FAILING_AND_PASSING","buildId":337254943,"containerId":"245c3ef336308a804afbb69a62ad430ebea23b7ffcfe7308bea3fb7c994dba6b","dateReproducedBuildStr":"22/08/18 10:46","dateReproducedBuild":{"$date":"2018-08-22T10:46:37.990Z"},"dayReproducedBuild":"22/08/2018","hostname":"spirals-bears","status":"TREATED"}
{"runId":"d75f4a89-740d-4a70-a89e-2e09374fb945_02-18-week1-FAILING_AND_PASSING","buildId":337909441,"containerId":"833cd235dfc4e1912cc9dc2f949aefe48c586606ba06ab7652b60ebe77f24c3f","dateReproducedBuildStr":"22/08/18 10:49","dateReproducedBuild":{"$date":"2018-08-22T10:49:34.542Z"},"dayReproducedBuild":"22/08/2018","hostname":"spirals-bears","status":"TREATED"}
{"runId":"d75f4a89-740d-4a70-a89e-2e09374fb945_02-18-week1-FAILING_AND_PASSING","buildId":338121462,"containerId":"ac0f1714bf5e96cca7ba3e16698cc6a175380c80aaf534bc42db532abc433855","dateReproducedBuildStr":"22/08/18 11:01","dateReproducedBuild":{"$date":"2018-08-22T11:01:36.649Z"},"dayReproducedBuild":"22/08/2018","hostname":"spirals-bears","status":"TREATED"}
{"runId":"d75f4a89-740d-4a70-a89e-2e09374fb945_02-18-week1-FAILING_AND_PASSING","buildId":338603736,"containerId":"0622b35bf329ce880519497c2e991d44a6f413b55b8db535795e08a1bac0b7ea","dateReproducedBuildStr":"22/08/18 11:06","dateReproducedBuild":{"$date":"2018-08-22T11:06:36.677Z"},"dayReproducedBuild":"22/08/2018","hostname":"spirals-bears","status":"TREATED"}
{"runId":"d75f4a89-740d-4a70-a89e-2e09374fb945_02-18-week1-FAILING_AND_PASSING","buildId":336563220,"containerId":"a0db9a29fcfce79d46851d200e7e3f01cb35a49a40e4cdfd1cc088cf382ca07f","dateReproducedBuildStr":"22/08/18 11:10","dateReproducedBuild":{"$date":"2018-08-22T11:10:32.955Z"},"dayReproducedBuild":"22/08/2018","hostname":"spirals-bears","status":"TREATED"}
{"runId":"d75f4a89-740d-4a70-a89e-2e09374fb945_02-18-week1-FAILING_AND_PASSING","buildId":338439832,"containerId":"32397494cbcf65ace89c09b1c8696f0f72c1d82b4fb17c1e6f7b0e81764c7a1f","dateReproducedBuildStr":"22/08/18 11:35","dateReproducedBuild":{"$date":"2018-08-22T11:35:48.742Z"},"dayReproducedBuild":"22/08/2018","hostname":"spirals-bears","status":"TREATED"}
{"runId":"d75f4a89-740d-4a70-a89e-2e09374fb945_02-18-week1-FAILING_AND_PASSING","buildId":337535538,"containerId":"38a498b222c7ebee2f20d1e8ff9d35cc5ac07d54e9d599f880cb4bb4f3d27e9f","dateReproducedBuildStr":"22/08/18 11:47","dateReproducedBuild":{"$date":"2018-08-22T11:47:21.093Z"},"dayReproducedBuild":"22/08/2018","hostname":"spirals-bears","status":"TREATED"}
{"runId":"d75f4a89-740d-4a70-a89e-2e09374fb945_02-18-week1-FAILING_AND_PASSING","buildId":338016101,"containerId":"111b30a3d065bb80055459783956679450c8e90629042301cd0ac7617e0fccf2","dateReproducedBuildStr":"22/08/18 11:50","dateReproducedBuild":{"$date":"2018-08-22T11:50:15.416Z"},"dayReproducedBuild":"22/08/2018","hostname":"spirals-bears","status":"TREATED"}
{"runId":"d75f4a89-740d-4a70-a89e-2e09374fb945_02-18-week1-FAILING_AND_PASSING","buildId":335027721,"containerId":"789cfb5bd262d67fd97be27a91ee83f755f982d51b90e107a69b01102dd8b31d","dateReproducedBuildStr":"22/08/18 12:40","dateReproducedBuild":{"$date":"2018-08-22T12:40:24.196Z"},"dayReproducedBuild":"22/08/2018","hostname":"spirals-bears","status":"TREATED"}
